{
  "version": "6",
  "dialect": "sqlite",
  "id": "e3010ebe-b98f-4d0b-9a8e-5fdfd1164d27",
  "prevId": "5ad1f002-2e48-4595-b8e7-a86cc0ac937b",
  "tables": {
    "cars": {
      "name": "cars",
      "columns": {
        "id": {
          "name": "id",
          "type": "integer",
          "primaryKey": true,
          "notNull": true,
          "autoincrement": true
        },
        "ordinal": {
          "name": "ordinal",
          "type": "integer",
          "primaryKey": false,
          "notNull": true,
          "autoincrement": false
        },
        "class": {
          "name": "class",
          "type": "integer",
          "primaryKey": false,
          "notNull": true,
          "autoincrement": false
        },
        "displayName": {
          "name": "displayName",
          "type": "text",
          "primaryKey": false,
          "notNull": false,
          "autoincrement": false
        }
      },
      "indexes": {
        "cars_ordinal_unique": {
          "name": "cars_ordinal_unique",
          "columns": [
            "ordinal"
          ],
          "isUnique": true
        }
      },
      "foreignKeys": {},
      "compositePrimaryKeys": {},
      "uniqueConstraints": {},
      "checkConstraints": {}
    },
    "events": {
      "name": "events",
      "columns": {
        "id": {
          "name": "id",
          "type": "integer",
          "primaryKey": true,
          "notNull": true,
          "autoincrement": true
        },
        "name": {
          "name": "name",
          "type": "text",
          "primaryKey": false,
          "notNull": true,
          "autoincrement": false
        },
        "type": {
          "name": "type",
          "type": "text",
          "primaryKey": false,
          "notNull": true,
          "autoincrement": false
        },
        "createdAt": {
          "name": "createdAt",
          "type": "integer",
          "primaryKey": false,
          "notNull": true,
          "autoincrement": false,
          "default": "(unixepoch())"
        }
      },
      "indexes": {
        "events_name_type_unq": {
          "name": "events_name_type_unq",
          "columns": [
            "name",
            "type"
          ],
          "isUnique": true
        }
      },
      "foreignKeys": {},
      "compositePrimaryKeys": {},
      "uniqueConstraints": {},
      "checkConstraints": {}
    },
    "laps": {
      "name": "laps",
      "columns": {
        "id": {
          "name": "id",
          "type": "integer",
          "primaryKey": true,
          "notNull": true,
          "autoincrement": true
        },
        "sessionId": {
          "name": "sessionId",
          "type": "integer",
          "primaryKey": false,
          "notNull": true,
          "autoincrement": false
        },
        "lapNumber": {
          "name": "lapNumber",
          "type": "integer",
          "primaryKey": false,
          "notNull": true,
          "autoincrement": false
        },
        "timeMs": {
          "name": "timeMs",
          "type": "integer",
          "primaryKey": false,
          "notNull": true,
          "autoincrement": false
        },
        "framesBlob": {
          "name": "framesBlob",
          "type": "blob",
          "primaryKey": false,
          "notNull": true,
          "autoincrement": false
        }
      },
      "indexes": {},
      "foreignKeys": {
        "laps_sessionId_sessions_id_fk": {
          "name": "laps_sessionId_sessions_id_fk",
          "tableFrom": "laps",
          "tableTo": "sessions",
          "columnsFrom": [
            "sessionId"
          ],
          "columnsTo": [
            "id"
          ],
          "onDelete": "no action",
          "onUpdate": "no action"
        }
      },
      "compositePrimaryKeys": {},
      "uniqueConstraints": {},
      "checkConstraints": {}
    },
    "sessions": {
      "name": "sessions",
      "columns": {
        "id": {
          "name": "id",
          "type": "integer",
          "primaryKey": true,
          "notNull": true,
          "autoincrement": true
        },
        "eventId": {
          "name": "eventId",
          "type": "integer",
          "primaryKey": false,
          "notNull": true,
          "autoincrement": false
        },
        "carId": {
          "name": "carId",
          "type": "integer",
          "primaryKey": false,
          "notNull": true,
          "autoincrement": false
        },
        "tuneLabel": {
          "name": "tuneLabel",
          "type": "text",
          "primaryKey": false,
          "notNull": false,
          "autoincrement": false
        },
        "piAtStart": {
          "name": "piAtStart",
          "type": "integer",
          "primaryKey": false,
          "notNull": true,
          "autoincrement": false
        },
        "startedAt": {
          "name": "startedAt",
          "type": "integer",
          "primaryKey": false,
          "notNull": true,
          "autoincrement": false
        },
        "endedAt": {
          "name": "endedAt",
          "type": "integer",
          "primaryKey": false,
          "notNull": false,
          "autoincrement": false
        }
      },
      "indexes": {},
      "foreignKeys": {
        "sessions_eventId_events_id_fk": {
          "name": "sessions_eventId_events_id_fk",
          "tableFrom": "sessions",
          "tableTo": "events",
          "columnsFrom": [
            "eventId"
          ],
          "columnsTo": [
            "id"
          ],
          "onDelete": "no action",
          "onUpdate": "no action"
        },
        "sessions_carId_cars_id_fk": {
          "name": "sessions_carId_cars_id_fk",
          "tableFrom": "sessions",
          "tableTo": "cars",
          "columnsFrom": [
            "carId"
          ],
          "columnsTo": [
            "id"
          ],
          "onDelete": "no action",
          "onUpdate": "no action"
        }
      },
      "compositePrimaryKeys": {},
      "uniqueConstraints": {},
      "checkConstraints": {}
    }
  },
  "views": {},
  "enums": {},
  "_meta": {
    "schemas": {},
    "tables": {},
    "columns": {}
  },
  "internal": {
    "indexes": {}
  }
}